odoo10_addon_sale_invoice_group_method-10.0.1.0.0-py2.7-nspkg.pth
odoo/addons/sale_invoice_group_method/README.rst
odoo/addons/sale_invoice_group_method/__init__.py
odoo/addons/sale_invoice_group_method/__manifest__.py
odoo/addons/sale_invoice_group_method/model/__init__.py
odoo/addons/sale_invoice_group_method/model/ir_model.py
odoo/addons/sale_invoice_group_method/model/partner.py
odoo/addons/sale_invoice_group_method/model/sale_invoice_group_method.py
odoo/addons/sale_invoice_group_method/model/sale_order.py
odoo/addons/sale_invoice_group_method/security/ir.model.access.csv
odoo/addons/sale_invoice_group_method/static/description/icon.png
odoo/addons/sale_invoice_group_method/tests/__init__.py
odoo/addons/sale_invoice_group_method/tests/test_sale_invoice_group_method.py
odoo/addons/sale_invoice_group_method/view/menu.xml
odoo/addons/sale_invoice_group_method/view/res_partner_view.xml
odoo/addons/sale_invoice_group_method/view/sale_invoice_group_method_view.xml
odoo/addons/sale_invoice_group_method/view/sale_order_view.xml
odoo10_addon_sale_invoice_group_method-10.0.1.0.0.dist-info/DESCRIPTION.rst
odoo10_addon_sale_invoice_group_method-10.0.1.0.0.dist-info/METADATA
odoo10_addon_sale_invoice_group_method-10.0.1.0.0.dist-info/RECORD
odoo10_addon_sale_invoice_group_method-10.0.1.0.0.dist-info/WHEEL
odoo10_addon_sale_invoice_group_method-10.0.1.0.0.dist-info/metadata.json
odoo10_addon_sale_invoice_group_method-10.0.1.0.0.dist-info/namespace_packages.txt
odoo10_addon_sale_invoice_group_method-10.0.1.0.0.dist-info/top_level.txt
